mysql_server/__init__.py
mysql_server/server.py
mcps_mysql_server-0.1.4.dist-info/METADATA
mcps_mysql_server-0.1.4.dist-info/WHEEL
mcps_mysql_server-0.1.4.dist-info/entry_points.txt
mcps_mysql_server-0.1.4.dist-info/RECORD
