Metadata-Version: 2.4
Name: mcps-mysql-server
Version: 0.1.4
Summary: MySQL server implementation for MCP (Model Control Protocol) framework
Author-email: Shubham Rampurkar <rampurkarshubham91@gmail.com>
License-Expression: MIT
Requires-Python: >=3.8
Requires-Dist: httpx>=0.28.1
Requires-Dist: mcp[cli]>=1.9.3
Requires-Dist: mysql-connector-python>=9.3.0
